{"_invocation_id": "b96362b2-20ac-484c-ad4b-5b761d95bc4e", "linked": {"0": {"name": "source.f1_project.f1.drivers", "type": "source", "succ": [14, 20]}, "1": {"name": "source.f1_project.f1.constructors", "type": "source", "succ": [20]}, "2": {"name": "source.f1_project.f1.circuits", "type": "source"}, "3": {"name": "source.f1_project.f1.race_statuscodes", "type": "source"}, "4": {"name": "source.f1_project.f1.races", "type": "source", "succ": [14, 16, 25]}, "5": {"name": "source.f1_project.f1.results", "type": "source", "succ": [11]}, "6": {"name": "source.f1_project.f1.constructor_standings", "type": "source"}, "7": {"name": "source.f1_project.f1.constructor_results", "type": "source"}, "8": {"name": "source.f1_project.f1.driver_standings", "type": "source"}, "9": {"name": "source.f1_project.f1.lap_times", "type": "source"}, "10": {"name": "source.f1_project.f1.pit_stops", "type": "source"}, "11": {"name": "model.f1_project.adjusted_results", "type": "model", "succ": [15, 20]}, "12": {"name": "model.f1_project.modern_points_system", "type": "model", "succ": [11]}, "13": {"name": "model.f1_project.points_for_fastest_lap", "type": "model", "succ": [15, 20]}, "14": {"name": "model.f1_project.career_points_table", "type": "model", "succ": [18]}, "15": {"name": "model.f1_project.driver_adjusted_results_with_bonus", "type": "model", "succ": [14]}, "16": {"name": "model.f1_project.max_year", "type": "model", "succ": [14]}, "17": {"name": "model.f1_project.DriverPerformance", "type": "model"}, "18": {"name": "model.f1_project.final_output_table", "type": "model", "succ": [17]}, "19": {"name": "model.f1_project.base_table", "type": "model", "succ": [22]}, "20": {"name": "model.f1_project.team_adjusted_results_with_bonus", "type": "model", "succ": [19]}, "21": {"name": "model.f1_project.gaps_and_islands_table", "type": "model", "succ": [27]}, "22": {"name": "model.f1_project.pairs_table", "type": "model", "succ": [21, 23]}, "23": {"name": "model.f1_project.percentile_metrics", "type": "model", "succ": [21]}, "24": {"name": "model.f1_project.TeamStrategy", "type": "model", "succ": [26]}, "25": {"name": "model.f1_project.team_final_output_table_filtered", "type": "model", "succ": [24]}, "26": {"name": "model.f1_project.TeamStrategyAggregated", "type": "model"}, "27": {"name": "model.f1_project.team_final_output_table", "type": "model", "succ": [25]}}}